quantcrypt/__init__.py
quantcrypt/cipher.py
quantcrypt/compiler.py
quantcrypt/dss.py
quantcrypt/errors.py
quantcrypt/kdf.py
quantcrypt/kem.py
quantcrypt/utils.py
quantcrypt/internal/chunksize.py
quantcrypt/internal/compiler.py
quantcrypt/internal/constants.py
quantcrypt/internal/errors.py
quantcrypt/internal/pqclean.py
quantcrypt/internal/utils.py
quantcrypt/internal/bin/falcon_1024_clean.cpython-312-darwin.so
quantcrypt/internal/bin/falcon_512_clean.cpython-312-darwin.so
quantcrypt/internal/bin/ml_dsa_44_clean.cpython-312-darwin.so
quantcrypt/internal/bin/ml_dsa_65_clean.cpython-312-darwin.so
quantcrypt/internal/bin/ml_dsa_87_clean.cpython-312-darwin.so
quantcrypt/internal/bin/ml_kem_1024_clean.cpython-312-darwin.so
quantcrypt/internal/bin/ml_kem_512_clean.cpython-312-darwin.so
quantcrypt/internal/bin/ml_kem_768_clean.cpython-312-darwin.so
quantcrypt/internal/bin/sphincs_shake_256f_simple_clean.cpython-312-darwin.so
quantcrypt/internal/bin/sphincs_shake_256s_simple_clean.cpython-312-darwin.so
quantcrypt/internal/cipher/krypton.py
quantcrypt/internal/cipher/krypton_file.py
quantcrypt/internal/cipher/krypton_kem.py
quantcrypt/internal/cli/annotations.py
quantcrypt/internal/cli/console.py
quantcrypt/internal/cli/main.py
quantcrypt/internal/cli/tools.py
quantcrypt/internal/cli/commands/compile.py
quantcrypt/internal/cli/commands/enc_dec.py
quantcrypt/internal/cli/commands/info.py
quantcrypt/internal/cli/commands/keygen.py
quantcrypt/internal/cli/commands/remove.py
quantcrypt/internal/cli/commands/sign_verify.py
quantcrypt/internal/kdf/argon2_kdf.py
quantcrypt/internal/kdf/common.py
quantcrypt/internal/kdf/kmac_kdf.py
quantcrypt/internal/pqa/base_dss.py
quantcrypt/internal/pqa/base_kem.py
quantcrypt/internal/pqa/common.py
quantcrypt/internal/pqa/dss_algos.py
quantcrypt/internal/pqa/kem_algos.py
quantcrypt/pqclean/.gitkeep
quantcrypt-1.0.0.dist-info/METADATA
quantcrypt-1.0.0.dist-info/WHEEL
quantcrypt-1.0.0.dist-info/entry_points.txt
quantcrypt-1.0.0.dist-info/licenses/LICENSE
quantcrypt-1.0.0.dist-info/RECORD
