Metadata-Version: 2.4
Name: quantcrypt
Version: 1.0.0
Summary: Cross-platform Python library for Post-Quantum Cryptography using precompiled PQClean binaries
Project-URL: Repository, https://github.com/aabmets/quantcrypt
Project-URL: Documentation, https://github.com/aabmets/quantcrypt/wiki
Project-URL: Bug Tracker, https://github.com/aabmets/quantcrypt/issues
Author-email: Mattias Aabmets <mattias.aabmets@gmail.com>
License-Expression: MIT
License-File: LICENSE
Keywords: crypto,cryptography,post-quantum,pqclean,security
Classifier: Development Status :: 5 - Production/Stable
Classifier: Intended Audience :: Developers
Classifier: License :: OSI Approved :: MIT License
Classifier: Natural Language :: English
Classifier: Operating System :: MacOS
Classifier: Operating System :: Microsoft :: Windows
Classifier: Operating System :: POSIX :: Linux
Classifier: Programming Language :: Python :: 3.10
Classifier: Programming Language :: Python :: 3.11
Classifier: Programming Language :: Python :: 3.12
Classifier: Programming Language :: Python :: 3.13
Classifier: Topic :: Security
Classifier: Topic :: Security :: Cryptography
Classifier: Topic :: Software Development
Classifier: Topic :: Software Development :: Libraries
Requires-Python: >=3.10
Requires-Dist: argon2-cffi>=23.1.0
Requires-Dist: dotmap>=1.3.30
Requires-Dist: orjson>=3.10.0
Requires-Dist: pycryptodomex>=3.20.0
Requires-Dist: pydantic>=2.9.0
Requires-Dist: rich>=13.8.0
Requires-Dist: typer>=0.15.0
Requires-Dist: types-zxcvbn>=4.5.0
Requires-Dist: zxcvbn>=4.5.0
Provides-Extra: compiler
Requires-Dist: cffi>=1.17.0; extra == 'compiler'
Requires-Dist: pyyaml>=6.0.1; extra == 'compiler'
Requires-Dist: requests>=2.31.0; extra == 'compiler'
Requires-Dist: setuptools>=70.0.0; extra == 'compiler'
